{
	"author":"JetBrains",
	"name":"RustRover",
	"logo":"https://resources.jetbrains.com/storage/logos/web/rustrover/rustrover.svg",
	"description":"面向 Rust 开发者的强大 IDE。",
	"category":"development",
	"version":"2025.3.1(253.29346.139)",
	"platform":"linux",
	"url":{
		"RustRover-2025.3.1-aarch64.tar.gz":"https://download.jetbrains.com/rustrover/RustRover-2025.3.1-aarch64.tar.gz",
		"RustRover-2025.3.1.tar.gz":"https://download.jetbrains.com/rustrover/RustRover-2025.3.1.tar.gz"
	},
	"homepage":"https://www.jetbrains.com/zh-cn/rust/",
	"script":{
		"args":{
			"codes":"RR"
		},
		"name":"jetbrains-product"
	}
}